hahaha/__init__.py
hahaha/bang.py
hahaha/dog.py
hahaha/util.py
hahaha/template-imgs/__init__.py
hahaha-0.0.1.dist-info/METADATA
hahaha-0.0.1.dist-info/WHEEL
hahaha-0.0.1.dist-info/top_level.txt
hahaha-0.0.1.dist-info/RECORD
