Metadata-Version: 2.1
Name: hahaha
Version: 0.0.1
Summary: biaoqingbao
Home-page: UNKNOWN
Author: leyan zhu, zhaokai wang
Author-email: UNKNOWN
License: UNKNOWN
Platform: UNKNOWN
